djangofobi_email_router/__init__.py
djangofobi_email_router/constants.py
djangofobi_email_router/fobi_form_handlers.py
djangofobi_email_router/forms.py
djangofobi_email_router/locale/fr/LC_MESSAGES/django.mo
djangofobi_email_router/locale/fr/LC_MESSAGES/django.po
djangofobi_email_router/templates/email_router/plugin_data_repr.html
djangofobi_email_router-1.2.3.dist-info/METADATA
djangofobi_email_router-1.2.3.dist-info/WHEEL
djangofobi_email_router-1.2.3.dist-info/licenses/LICENSE
djangofobi_email_router-1.2.3.dist-info/RECORD
