Metadata-Version: 2.4
Name: djangofobi-email-router
Version: 1.2.3
Summary: A django-fobi handler plugin to send the content of a form to different e-mails addresses, depending on a value of a form field.
License: GPL-3.0-or-later
License-File: LICENSE
Author: KAPT dev team
Author-email: dev@kapt.mobi
Requires-Python: >3.9
Classifier: License :: OSI Approved :: GNU General Public License v3 or later (GPLv3+)
Classifier: Programming Language :: Python :: 3
Classifier: Programming Language :: Python :: 3.10
Classifier: Programming Language :: Python :: 3.11
Classifier: Programming Language :: Python :: 3.12
Classifier: Programming Language :: Python :: 3.13
Classifier: Programming Language :: Python :: 3.14
Requires-Dist: Django (>=1.11)
Requires-Dist: django-fobi (>=0.17.0)
Project-URL: Repository, https://gitlab.com/kapt/open-source/djangofobi-email-router
